omnifusion/__init__.py
omnifusion-0.0.0a1.dist-info/LICENSE
omnifusion-0.0.0a1.dist-info/METADATA
omnifusion-0.0.0a1.dist-info/WHEEL
omnifusion-0.0.0a1.dist-info/RECORD
