Metadata-Version: 2.1
Name: omnifusion
Version: 0.0.0a1
Summary: Placeholder package to reserve the omnifusion namespace.
License: BSD-3-Clause
Author: Prodigal AI
Author-email: info@prodigal.ai
Requires-Python: >=3.9,<4.0
Classifier: License :: OSI Approved :: BSD License
Classifier: Programming Language :: Python :: 3
Classifier: Programming Language :: Python :: 3.9
Classifier: Programming Language :: Python :: 3.10
Classifier: Programming Language :: Python :: 3.11
Classifier: Programming Language :: Python :: 3.12
